<?xml version="1.0" encoding="utf-8" ?>
<dwsync>
<file name="file-16.gif" server="101.226.179.80//data/www/web/" local="130880581397479905" remote="130944023860000000" />
<file name="file-64.gif" server="101.226.179.80//data/www/web/" local="130880581397489905" remote="130944023860000000" />
<file name="folder-16.gif" server="101.226.179.80//data/www/web/" local="130880581397499906" remote="130944023870000000" />
<file name="folder-64.gif" server="101.226.179.80//data/www/web/" local="130880581397509906" remote="130944023870000000" />
<file name="go-up.gif" server="101.226.179.80//data/www/web/" local="130880581397509906" remote="130944023870000000" />
<file name="file-16.gif" server="678995.ichengyun.net" local="130880581397479905" remote="130944628200000000" />
<file name="file-64.gif" server="678995.ichengyun.net" local="130880581397489905" remote="130944628200000000" />
<file name="folder-16.gif" server="678995.ichengyun.net" local="130880581397499906" remote="130944628200000000" />
<file name="folder-64.gif" server="678995.ichengyun.net" local="130880581397509906" remote="130944628200000000" />
<file name="go-up.gif" server="678995.ichengyun.net" local="130880581397509906" remote="130944628200000000" />
<file name="file-16.gif" server="678995.ichengyun.net/public_html/" local="130880581397479905" remote="130944666000000000" />
<file name="file-64.gif" server="678995.ichengyun.net/public_html/" local="130880581397489905" remote="130944666000000000" />
<file name="folder-16.gif" server="678995.ichengyun.net/public_html/" local="130880581397499906" remote="130944666000000000" />
<file name="folder-64.gif" server="678995.ichengyun.net/public_html/" local="130880581397509906" remote="130944666000000000" />
<file name="go-up.gif" server="678995.ichengyun.net/public_html/" local="130880581397509906" remote="130944666000000000" />
</dwsync>